cpca/__init__.py
cpca/drawer.py
cpca/exceptions.py
cpca/matcher.py
cpca/structures.py
cpca/resources/56_nations.csv
cpca/resources/__init__.py
cpca/resources/adcodes.csv
cpcax-0.6.1.dist-info/LICENSE
cpcax-0.6.1.dist-info/METADATA
cpcax-0.6.1.dist-info/WHEEL
cpcax-0.6.1.dist-info/top_level.txt
cpcax-0.6.1.dist-info/RECORD
