Metadata-Version: 2.1
Name: cpcax
Version: 0.6.1
Summary: Chinese Province, City and Area Recognition Utilities. This is an extended version based on https://github.com/DQinYuan/chinese_province_city_area_mapper
Home-page: http://pypi.python.org/pypi/cpcax/
Author: Zhang
Author-email: oo@zju.edu.cn
License: LICENSE
License-File: LICENSE
Requires-Dist: pyahocorasick
Requires-Dist: progress
Requires-Dist: jinja2 (==3.0.0)
Requires-Dist: folium
Requires-Dist: pyecharts (>=1.9.0)
